mockdock/__init__.py
mockdock/dns.py
mockdock/server.py
mockdock-0.8.1.dist-info/LICENSE
mockdock-0.8.1.dist-info/METADATA
mockdock-0.8.1.dist-info/WHEEL
mockdock-0.8.1.dist-info/entry_points.txt
mockdock-0.8.1.dist-info/top_level.txt
mockdock-0.8.1.dist-info/RECORD
