Metadata-Version: 2.1
Name: mockdock
Version: 0.8.1
Summary: mockdock is a dns resolver and http server usable for testing containers
Home-page: https://github.com/jensstein/mockdock
License: MIT
Platform: UNKNOWN
Provides: mockdock
Requires-Dist: conu
Provides-Extra: dev
Requires-Dist: mypy ; extra == 'dev'
